COPYING.LESSER
LICENSE.txt
MANIFEST.in
README.md
README.rst
requirements.txt
setup.py
PyMeeus.egg-info/PKG-INFO
PyMeeus.egg-info/SOURCES.txt
PyMeeus.egg-info/dependency_links.txt
PyMeeus.egg-info/top_level.txt
docs/Makefile
docs/README.txt
docs/build/html/.buildinfo
docs/build/html/.nojekyll
docs/build/html/genindex.html
docs/build/html/index.html
docs/build/html/objects.inv
docs/build/html/py-modindex.html
docs/build/html/search.html
docs/build/html/searchindex.js
docs/build/html/_modules/index.html
docs/build/html/_modules/pymeeus/Angle.html
docs/build/html/_modules/pymeeus/Coordinates.html
docs/build/html/_modules/pymeeus/CurveFitting.html
docs/build/html/_modules/pymeeus/Earth.html
docs/build/html/_modules/pymeeus/Epoch.html
docs/build/html/_modules/pymeeus/Interpolation.html
docs/build/html/_modules/pymeeus/Jupiter.html
docs/build/html/_modules/pymeeus/JupiterMoons.html
docs/build/html/_modules/pymeeus/Mars.html
docs/build/html/_modules/pymeeus/Mercury.html
docs/build/html/_modules/pymeeus/Minor.html
docs/build/html/_modules/pymeeus/Moon.html
docs/build/html/_modules/pymeeus/Neptune.html
docs/build/html/_modules/pymeeus/Pluto.html
docs/build/html/_modules/pymeeus/Saturn.html
docs/build/html/_modules/pymeeus/Sun.html
docs/build/html/_modules/pymeeus/Uranus.html
docs/build/html/_modules/pymeeus/Venus.html
docs/build/html/_modules/pymeeus/base.html
docs/build/html/_sources/index.rst.txt
docs/build/html/_sources/bodies/Earth.rst.txt
docs/build/html/_sources/bodies/Jupiter.rst.txt
docs/build/html/_sources/bodies/JupiterMoons.rst.txt
docs/build/html/_sources/bodies/Mars.rst.txt
docs/build/html/_sources/bodies/Mercury.rst.txt
docs/build/html/_sources/bodies/Minor.rst.txt
docs/build/html/_sources/bodies/Moon.rst.txt
docs/build/html/_sources/bodies/Neptune.rst.txt
docs/build/html/_sources/bodies/Pluto.rst.txt
docs/build/html/_sources/bodies/Saturn.rst.txt
docs/build/html/_sources/bodies/Sun.rst.txt
docs/build/html/_sources/bodies/Uranus.rst.txt
docs/build/html/_sources/bodies/Venus.rst.txt
docs/build/html/_sources/bodies/index.rst.txt
docs/build/html/_sources/core/Angle.rst.txt
