Metadata-Version: 1.1
Name: PyMeeus
Version: 0.5.7
Summary: Python implementation of Jean Meeus astronomical routines
Home-page: https://github.com/architest/pymeeus
Author: Dagoberto Salazar
Author-email: dagoberto.salazar@gmail.com
License: LGPLv3
Download-URL: https://github.com/architest/pymeeus
Keywords: Meeus astronomy module library
Platform: UNKNOWN
Classifier: Development Status :: 4 - Beta
Classifier: Environment :: Console
Classifier: Intended Audience :: Developers
Classifier: Intended Audience :: Education
Classifier: Intended Audience :: Science/Research
Classifier: License :: OSI Approved :: GNU Lesser General Public License v3 (LGPLv3)
Classifier: Operating System :: OS Independent
Classifier: Programming Language :: Python :: 2.7
Classifier: Programming Language :: Python :: 3.6
Classifier: Topic :: Scientific/Engineering :: Astronomy
